{
  "todos": [
    {
      "todo": "AOJSndjonasd",
      "completed": true,
      "id": 1
    },
    {
      "todo": "AK SDK AS DS",
      "completed": true,
      "id": 2
    },
    {
      "todo": "KA SDASJDJASNDOASDOASODASKOD",
      "completed": true,
      "id": 3
    },
    {
      "todo": "AKSJDJKASJDANSKDNASDASD",
      "completed": true,
      "id": 4
    },
    {
      "todo": "AKJSDKJASDKASDASDNAJNDKSNJAKSD",
      "completed": false,
      "id": 5
    },
    {
      "todo": "asdlasndoadknas",
      "completed": false,
      "id": 6
    }
  ]
}